replicate_github-1.0.0.dist-info/DESCRIPTION.rst
replicate_github-1.0.0.dist-info/METADATA
replicate_github-1.0.0.dist-info/RECORD
replicate_github-1.0.0.dist-info/WHEEL
replicate_github-1.0.0.dist-info/entry_points.txt
replicate_github-1.0.0.dist-info/metadata.json
replicate_github-1.0.0.dist-info/top_level.txt
replicategithub/__init__.py
replicategithub/cli.py
replicategithub/mirror.py
replicategithub/webhook.py
