Metadata-Version: 2.0
Name: replicate-github
Version: 1.0.0
Summary: Tool for maintaining mirrors of GitHub repos
Home-page: http://github.com/danielparks/replicate-github
Author: Daniel Parks
Author-email: os-replicate-github@demonhorse.org
License: BSD
Platform: UNKNOWN
Classifier: Development Status :: 5 - Production/Stable
Classifier: Intended Audience :: Developers
Classifier: Intended Audience :: System Administrators
Classifier: License :: OSI Approved :: BSD License
Classifier: Natural Language :: English
Classifier: Programming Language :: Python :: 3
Classifier: Topic :: Software Development :: Version Control
Classifier: Topic :: System :: Archiving :: Mirroring
Requires-Dist: click
Requires-Dist: gitpython
Requires-Dist: pygithub
Requires-Dist: pyyaml
